purnamatools/__init__.py
purnamatools/evaluate.py
purnamatools/feature_selection.py
purnamatools/forecasting.py
purnamatools/initial_check.py
purnamatools-0.2.3.dist-info/licenses/LICENSE
purnamatools-0.2.3.dist-info/METADATA
purnamatools-0.2.3.dist-info/WHEEL
purnamatools-0.2.3.dist-info/top_level.txt
purnamatools-0.2.3.dist-info/RECORD
