Metadata-Version: 2.4
Name: purnamatools
Version: 0.2.3
Summary: Python package to simplify the initial stages of model building and analysis for data science projects
Home-page: https://github.com/PurnamaRidzkyN/purnamatools.git
Author: Purnama Ridzky Nugraha
Author-email: purnamanugraha492@gmail.com
Keywords: data-science machine-learning feature-selection model-analysis
Classifier: Programming Language :: Python :: 3
Classifier: License :: OSI Approved :: MIT License
Classifier: Operating System :: OS Independent
Classifier: Intended Audience :: Science/Research
Classifier: Topic :: Scientific/Engineering :: Artificial Intelligence
Classifier: Topic :: Software Development :: Libraries
Requires-Python: >=3.8
License-File: LICENSE
Requires-Dist: pandas>=1.3.0
Requires-Dist: numpy>=1.21.0
Requires-Dist: seaborn>=0.11.0
Requires-Dist: matplotlib>=3.4.0
Requires-Dist: scikit-learn>=1.0.0
Dynamic: author
Dynamic: author-email
Dynamic: classifier
Dynamic: description
Dynamic: description-content-type
Dynamic: home-page
Dynamic: keywords
Dynamic: license-file
Dynamic: requires-dist
Dynamic: requires-python
Dynamic: summary
